gpu_tracking-2.0.0.dist-info/METADATA
gpu_tracking-2.0.0.dist-info/WHEEL
gpu_tracking-2.0.0.dist-info/entry_points.txt
gpu_tracking/generated.py
gpu_tracking/lib.py
gpu_tracking/__init__.py
gpu_tracking/docs/index.rst
gpu_tracking/docs/python_api/link.rst
gpu_tracking/docs/python_api/batch.rst
gpu_tracking/docs/python_api/mean_from_file.rst
gpu_tracking/docs/python_api/load.rst
gpu_tracking/docs/python_api/connect.rst
gpu_tracking/docs/python_api/characterize_points.rst
gpu_tracking/docs/python_api/toc.rst
gpu_tracking/docs/python_api/LoG.rst
gpu_tracking/docs/app/tour.rst
gpu_tracking/docs/app/Overview.png
gpu_tracking/docs/app/toc.rst
gpu_tracking/docs/Makefile
gpu_tracking/docs/conf.py
gpu_tracking/docs/make.bat
gpu_tracking/docs/static/custom.css
gpu_tracking/docs/_build/html/python_api/mean_from_file.html
gpu_tracking/docs/_build/html/python_api/link.html
gpu_tracking/docs/_build/html/python_api/load.html
gpu_tracking/docs/_build/html/python_api/toc.html
gpu_tracking/docs/_build/html/python_api/characterize_points.html
gpu_tracking/docs/_build/html/python_api/batch.html
gpu_tracking/docs/_build/html/python_api/LoG.html
gpu_tracking/docs/_build/html/python_api/connect.html
gpu_tracking/docs/_build/html/index.html
gpu_tracking/docs/_build/html/app/toc.html
gpu_tracking/docs/_build/html/app/tour.html
gpu_tracking/docs/_build/html/searchindex.js
gpu_tracking/docs/_build/html/_sources/python_api/connect.rst.txt
gpu_tracking/docs/_build/html/_sources/python_api/batch.rst.txt
gpu_tracking/docs/_build/html/_sources/python_api/toc.rst.txt
gpu_tracking/docs/_build/html/_sources/python_api/load.rst.txt
gpu_tracking/docs/_build/html/_sources/python_api/LoG.rst.txt
gpu_tracking/docs/_build/html/_sources/python_api/characterize_points.rst.txt
gpu_tracking/docs/_build/html/_sources/python_api/link.rst.txt
gpu_tracking/docs/_build/html/_sources/python_api/mean_from_file.rst.txt
gpu_tracking/docs/_build/html/_sources/app/tour.rst.txt
gpu_tracking/docs/_build/html/_sources/app/toc.rst.txt
gpu_tracking/docs/_build/html/_sources/index.rst.txt
gpu_tracking/docs/_build/html/_static/plus.png
gpu_tracking-2.0.0.dist-info/RECORD
