Metadata-Version: 2.1
Name: gpu_tracking
Version: 2.0.0
Requires-Dist: numpy
Requires-Dist: pandas
Requires-Dist: tqdm
